connect/devops_testing/__init__.py
connect/devops_testing/asserts.py
connect/devops_testing/bdd/__init__.py
connect/devops_testing/bdd/fixtures.py
connect/devops_testing/bdd/steps.py
connect/devops_testing/fixtures.py
connect/devops_testing/request.py
connect/devops_testing/utils.py
connect_devops_testing_library-25.2.dist-info/LICENSE
connect_devops_testing_library-25.2.dist-info/METADATA
connect_devops_testing_library-25.2.dist-info/WHEEL
connect_devops_testing_library-25.2.dist-info/RECORD
