Metadata-Version: 2.1
Name: connect-devops-testing-library
Version: 25.2
Summary: Testing framework to ease Connect EaaS Processors development.
Home-page: https://github.com/cloudblue/connect-devops-testing-library
License: Apache-2.0
Keywords: connect,eaas,testing,framework
Author: CloudBlue LLC
Requires-Python: >=3.7,<4
Classifier: License :: OSI Approved :: Apache Software License
Classifier: Programming Language :: Python :: 3
Classifier: Programming Language :: Python :: 3.7
Classifier: Programming Language :: Python :: 3.8
Classifier: Programming Language :: Python :: 3.9
Classifier: Programming Language :: Python :: 3.10
Classifier: Programming Language :: Python :: 3.11
Classifier: Programming Language :: Python :: 3.10
Classifier: Programming Language :: Python :: 3.11
Classifier: Programming Language :: Python :: 3.7
Classifier: Programming Language :: Python :: 3.8
Classifier: Programming Language :: Python :: 3.9
Classifier: Topic :: Software Development :: Build Tools
Classifier: Topic :: Software Development :: Libraries :: Python Modules
Requires-Dist: Faker (>=15.3.4,<16.0.0)
Requires-Dist: Pygments (>=2.13.0,<3.0.0)
Requires-Dist: behave (>=1.2,<2.0)
Requires-Dist: connect-openapi-client (>=25.0,<26.0)
Project-URL: Repository, https://github.com/cloudblue/connect-devops-testing-library
